KMeans_G2/KMeans_G2.py
KMeans_G2/__init__.py
KNN_G2/KNN_G2.py
KNN_G2/__init__.py
Package_G2-1.0.1.dist-info/METADATA
Package_G2-1.0.1.dist-info/Readme.md
Package_G2-1.0.1.dist-info/WHEEL
Package_G2-1.0.1.dist-info/top_level.txt
Package_G2-1.0.1.dist-info/RECORD
